LICENSE
MANIFEST.in
README.md
setup.cfg
setup.py
niemarkov/__init__.py
niemarkov/niemarkov.py
niemarkov.egg-info/PKG-INFO
niemarkov.egg-info/SOURCES.txt
niemarkov.egg-info/dependency_links.txt
niemarkov.egg-info/requires.txt
niemarkov.egg-info/top_level.txt