Metadata-Version: 2.1
Name: niemarkov
Version: 1.0.6
Summary: NieMarkov: Niema's Python implementation of Markov chains
Home-page: https://github.com/niemasd/NieMarkov
Author: Niema Moshiri
Author-email: niemamoshiri@gmail.com
Project-URL: Bug Reports, https://github.com/niemasd/NieMarkov/issues
Project-URL: Source, https://github.com/niemasd/NieMarkov
Keywords: python markov chain
Classifier: Development Status :: 3 - Alpha
Classifier: Intended Audience :: Developers
Classifier: Topic :: Software Development :: Build Tools
Classifier: License :: OSI Approved :: GNU General Public License v3 or later (GPLv3+)
Classifier: Programming Language :: Python :: 3
Classifier: Programming Language :: Python :: 3.7
Classifier: Programming Language :: Python :: 3.8
Classifier: Programming Language :: Python :: 3.9
Classifier: Programming Language :: Python :: 3.10
Classifier: Programming Language :: Python :: 3.11
Provides-Extra: dev
License-File: LICENSE
